scConGraph/__init__.py
scConGraph/scConGraph.py
scConGraph-0.1.18.dist-info/METADATA
scConGraph-0.1.18.dist-info/WHEEL
scConGraph-0.1.18.dist-info/top_level.txt
scConGraph-0.1.18.dist-info/RECORD
