Metadata-Version: 2.1
Name: scConGraph
Version: 0.1.18
Summary: A scalable cross-time Context Graph model for reconstructing tumor cell dynamic responses from single-cell perturbation transcriptomics.
Home-page: https://github.com/Li-Xinqi/scConGraph.git
Author: Xinqi Li
Author-email: lxq19@mails.tsinghua.edu.cn
License: MIT License
Classifier: Development Status :: 3 - Alpha
Classifier: Intended Audience :: Developers
Classifier: Topic :: Software Development :: Build Tools
Classifier: License :: OSI Approved :: MIT License
Classifier: Programming Language :: Python :: 3.7
Requires-Python: >=3.7
Requires-Dist: networkx >=2.6.3
Requires-Dist: matplotlib >=3.5.1
Requires-Dist: numpy >=1.21.5
Requires-Dist: pandas >=1.2.4
Requires-Dist: seaborn >=0.11.1
Requires-Dist: scipy >=1.7.3
Requires-Dist: scanpy >=1.9.3
Requires-Dist: scikit-learn >=1.0.2
Requires-Dist: community >=1.0.0b1
